Metadata-Version: 2.1
Name: Pacote-Calc-Dio
Version: 0.0.1
Summary: Calculadora
Author: Gilmar_Alexandre
Author-email: gilmar.alexandre.sc@outlook.com
License: MIT License
Keywords: Calculadora_gilmar
License-File: LICENSE
